mcbu_package/statistics.py
mcbu_package-0.0.1.dist-info/licenses/LICENSE
mcbu_package-0.0.1.dist-info/METADATA
mcbu_package-0.0.1.dist-info/WHEEL
mcbu_package-0.0.1.dist-info/top_level.txt
mcbu_package-0.0.1.dist-info/RECORD
