Metadata-Version: 2.4
Name: mcbu_package
Version: 0.0.1
Summary: A simple package for calculating statistics.
Author-email: Selin Altuntaş <slnaltuntas4@gmail.com>
Project-URL: Homepage, https://github.com/selinaltuntas/mcbu_package
Keywords: statistics,mean
Classifier: Development Status :: 3 - Alpha
Classifier: Intended Audience :: Developers
Classifier: License :: OSI Approved :: MIT License
Classifier: Programming Language :: Python :: 3
Classifier: Operating System :: OS Independent
Requires-Python: >=3.6
License-File: LICENSE
Dynamic: license-file
